tpu/__init__.py
tpu/main.py
tpu-0.1.0.dist-info/LICENSE.txt
tpu-0.1.0.dist-info/METADATA
tpu-0.1.0.dist-info/WHEEL
tpu-0.1.0.dist-info/top_level.txt
tpu-0.1.0.dist-info/RECORD
