Metadata-Version: 2.1
Name: tpu
Version: 0.1.0
Summary: A set of awesome scripts that aim to facilitate musicians with programming background ;)
Home-page: https://github.com/GeorgeVasiliadis/TPU
Author: George Vasiliadis
Author-email: geor.vasiliadis@gmail.com
License: LICENSE.txt
Platform: UNKNOWN
Classifier: Operating System :: OS Independent
Classifier: Programming Language :: Python :: 3
Classifier: Topic :: Software Development :: Libraries :: Python Modules
Classifier: Topic :: Text Processing :: General
Classifier: Topic :: Utilities
License-File: LICENSE.txt
